Workbook

Sheet Data
A1: Category | B1: City | C1: Container | D1: Customer ID | E1: Customer Name | F1: Customer Segment | G1: Department | H1: Item | I1: Item ID | J1: Order Date | K1: Order ID | L1: Order Priority | M1: Postal Code | N1: Region | O1: Row ID | P1: Ship Date | Q1: Ship Mode | R1: State | S1: Discount | T1: Order Quantity | U1: Product Base Margin | V1: Profit | W1: Sales | X1: Shipping Cost | Y1: Unit Price | Z1: Month Start | AA1: Year | AB1: Profit Margin
A2: Pens & Art Supplies | B2: Austin | C2: Wrap Bag | D2: 117 | E2: Linda Weiss | F2: Home Office | G2: Office Supplies | H2: Dixon Prang® Watercolor Pencils, 10-Color Set with Brush | I2: 11250 | J2: 42736 | K2: 7909 | L2: High | M2: 78745 | N2: Central | O2: 1074 | P2: 42737 | Q2: Regular Air | R2: Texas | S2: 0.03 | T2: 29 | U2: 0.44 | V2: 10 | W2: 122 | X2: 1 | Y2: 4 | Z2: =DATE(YEAR(J2),MONTH(J2),1) -> 0 | AA2: =YEAR(J2) -> 0 | AB2: =IFERROR(V2/W2,0) -> 0.081967213
A3: Pens & Art Supplies | B3: Lake Oswego | C3: Wrap Bag | D3: 114 | E3: Ron Newton | F3: Home Office | G3: Office Supplies | H3: Dixon Prang® Watercolor Pencils, 10-Color Set with Brush | I3: 11250 | J3: 42736 | K3: 89583 | L3: High | M3: 97035 | N3: West | O3: 19074 | P3: 42737 | Q3: Regular Air | R3: Oregon | S3: 0.03 | T3: 7 | U3: 0.44 | V3: 19 | W3: 30 | X3: 1 | Y3: 4 | Z3: =DATE(YEAR(J3),MONTH(J3),1) -> 0 | AA3: =YEAR(J3) -> 0 | AB3: =IFERROR(V3/W3,0) -> 0.63333333
A4: Computer Peripherals | B4: Baton Rouge | C4: Small Box | D4: 169 | E4: Janice Cole | F4: Corporate | G4: Technology | H4: Fellowes Mobile Numeric Keypad, Graphite | I4: 10886 | J4: 42736 | K4: 87463 | L4: Low | M4: 70802 | N4: South | O4: 19315 | P4: 42738 | Q4: Regular Air | R4: Louisiana | S4: 0.08 | T4: 3 | U4: 0.66 | V4: 280 | W4: 131 | X4: 17 | Y4: 43 | Z4: =DATE(YEAR(J4),MONTH(J4),1) -> 0 | AA4: =YEAR(J4) -> 0 | AB4: =IFERROR(V4/W4,0) -> 2.1374046
A5: Office Machines | B5: Baton Rouge | C5: Large Box | D5: 169 | E5: Janice Cole | F5: Corporate | G5: Technology | H5: Polycom ViaVideo™ Desktop Video Communications Unit | I5: 10293 | J5: 42736 | K5: 87463 | L5: Low | M5: 70802 | N5: South | O5: 19316 | P5: 42743 | Q5: Regular Air | R5: Louisiana | S5: 0.05 | T5: 12 | U5: 0.37 | V5: -112 | W5: 6945 | X5: 24 | Y5: 575 | Z5: =DATE(YEAR(J5),MONTH(J5),1) -> 0 | AA5: =YEAR(J5) -> 0 | AB5: =IFERROR(V5/W5,0) -> -0.01612671
A6: Paper | B6: Baton Rouge | C6: Wrap Bag | D6: 169 | E6: Janice Cole | F6: Corporate | G6: Office Supplies | H6: Staples Wirebound Steno Books, 6" x 9", 12/Pack | I6: 10279 | J6: 42736 | K6: 87463 | L6: Low | M6: 70802 | N6: South | O6: 19317 | P6: 42740 | Q6: Regular Air | R6: Louisiana | S6: 0.04 | T6: 3 | U6: 0.36 | V6: 25 | W6: 31 | X6: 2 | Y6: 10 | Z6: =DATE(YEAR(J6),MONTH(J6),1) -> 0 | AA6: =YEAR(J6) -> 0 | AB6: =IFERROR(V6/W6,0) -> 0.80645161
A7: Office Furnishings | B7: Draper | C7: Medium Box | D7: 1988 | E7: Anna Burgess | F7: Home Office | G7: Furniture | H7: 36X48 HARDFLOOR CHAIRMAT | I7: 10179 | J7: 42736 | K7: 89999 | L7: High | M7: 84020 | N7: West | O7: 19336 | P7: 42737 | Q7: Regular Air | R7: Utah | S7: 0.05 | T7: 3 | U7: 0.78 | V7: -181 | W7: 66 | X7: 21 | Y7: 21 | Z7: =DATE(YEAR(J7),MONTH(J7),1) -> 0 | AA7: =YEAR(J7) -> 0 | AB7: =IFERROR(V7/W7,0) -> -2.7424242
A8: Office Machines | B8: Layton | C8: Jumbo Drum | D8: 193 | E8: Danny Hong | F8: Corporate | G8: Technology | H8: Panasonic KX-P2130 Dot Matrix Printer | I8: 10680 | J8: 42736 | K8: 90430 | L8: Not Specified | M8: 84041 | N8: West | O8: 19663 | P8: 42738 | Q8: Delivery Truck | R8: Utah | S8: 0 | T8: 1 | U8: 0.59 | V8: -561 | W8: 224 | X8: 15 | Y8: 213 | Z8: =DATE(YEAR(J8),MONTH(J8),1) -> 0 | AA8: =YEAR(J8) -> 0 | AB8: =IFERROR(V8/W8,0) -> -2.5044643
A9: Storage & Organization | B9: Bowie | C9: Large Box | D9: 2211 | E9: Anita Hahn | F9: Home Office | G9: Office Supplies | H9: Safco Industrial Wire Shelving | I9: 10826 | J9: 42736 | K9: 88028 | L9: Not Specified | M9: 20715 | N9: East | O9: 19914 | P9: 42736 | Q9: Express Air | R9: Maryland | S9: 0.08 | T9: 2 | U9: 0 | V9: -425 | W9: 194 | X9: 35 | Y9: 96 | Z9: =DATE(YEAR(J9),MONTH(J9),1) -> 0 | AA9: =YEAR(J9) -> 0 | AB9: =IFERROR(V9/W9,0) -> -2.1907216
A10: Paper | B10: Kearney | C10: Small Box | D10: 388 | E10: Roger Schwartz | F10: Corporate | G10: Office Supplies | H10: Xerox 4200 Series MultiUse Premium Copy Paper (20Lb. and 84 Bright) | I10: 10893 | J10: 42736 | K10: 90337 | L10: Critical | M10: 68847 | N10: Central | O10: 22223 | P10: 42738 | Q10: Regular Air | R10: Nebraska | S10: 0.03 | T10: 4 | U10: 0.4 | V10: -52 | W10: 23 | X10: 6 | Y10: 5 | Z10: =DATE(YEAR(J10),MONTH(J10),1) -> 0 | AA10: =YEAR(J10) -> 0 | AB10: =IFERROR(V10/W10,0) -> -2.2608696
A11: Telephones and Communication | B11: Kearney | C11: Small Box | D11: 388 | E11: Roger Schwartz | F11: Corporate | G11: Technology | H11: T18 | I11: 10802 | J11: 42736 | K11: 90337 | L11: Critical | M11: 68847 | N11: Central | O11: 22224 | P11: 42739 | Q11: Regular Air | R11: Nebraska | S11: 0.01 | T11: 2 | U11: 0.57 | V11: -264 | W11: 189 | X11: 3 | Y11: 111 | Z11: =DATE(YEAR(J11),MONTH(J11),1) -> 0 | AA11: =YEAR(J11) -> 0 | AB11: =IFERROR(V11/W11,0) -> -1.3968254
A12: Tables | B12: Phenix City | C12: Jumbo Box | D12: 2579 | E12: Marshall Sutherland | F12: Home Office | G12: Furniture | H12: Bush Advantage Collection® Round Conference Table | I12: 10964 | J12: 42736 | K12: 88296 | L12: High | M12: 36869 | N12: South | O12: 23705 | P12: 42737 | Q12: Delivery Truck | R12: Alabama | S12: 0.09 | T12: 1 | U12: 0.64 | V12: -274 | W12: 175 | X12: 52 | Y12: 213 | Z12: =DATE(YEAR(J12),MONTH(J12),1) -> 0 | AA12: =YEAR(J12) -> 0 | AB12: =IFERROR(V12/W12,0) -> -1.5657143
A13: Binders and Binder Accessories | B13: Oxford | C13: Small Box | D13: 949 | E13: Ernest Oh | F13: Consumer | G13: Office Supplies | H13: Avery Trapezoid Ring Binder, 3" Capacity, Black, 1040 sheets | I13: 10302 | J13: 42737 | K13: 9285 | L13: Critical | M13: 1540 | N13: East | O13: 1279 | P13: 42737 | Q13: Regular Air | R13: Massachusetts | S13: 0.06 | T13: 3 | U13: 0.36 | V13: -19 | W13: 125 | X13: 3 | Y13: 41 | Z13: =DATE(YEAR(J13),MONTH(J13),1) -> 0 | AA13: =YEAR(J13) -> 0 | AB13: =IFERROR(V13/W13,0) -> -0.152
... A9427: Chairs & Chairmats | B9427: Oxford | C9427: Jumbo Drum | D9427: 2277 | E9427: Allison Peacock | F9427: Consumer | G9427: Furniture | H9427: Global High-Back Leather Tilter, Burgundy | I9427: 11166 | J9427: 44193 | K9427: 91506 | L9427: Not Specified | M9427: 1540 | N9427: East | O9427: 24554 | P9427: 44195 | Q9427: Delivery Truck | R9427: Massachusetts | S9427: 0 | T9427: 1 | U9427: 0.74 | V9427: -28 | W9427: 201 | X9427: 70 | Y9427: 123 | Z9427: =DATE(YEAR(J9427),MONTH(J9427),1) -> 0 | AA9427: =YEAR(J9427) -> 0 | AB9427: =IFERROR(V9427/W9427,0) -> -0.13930348

Sheet Monthly Trends
A1: MONTHLY PERFORMANCE
A2: Formula-driven monthly rollup with month-over-month and year-over-year growth.
A4: Month | B4: Sales | C4: Profit | D4: Units | E4: Orders | F4: MoM Sales Growth | G4: YoY Sales Growth
A5: 42736 | B5: =SUMIFS(Data!$W$2:$W$9427,Data!$Z$2:$Z$9427,A5) -> 149018 | C5: =SUMIFS(Data!$V$2:$V$9427,Data!$Z$2:$Z$9427,A5) -> -12762 | D5: =SUMIFS(Data!$T$2:$T$9427,Data!$Z$2:$Z$9427,A5) -> 1709 | E5: 135
A6: 42767 | B6: =SUMIFS(Data!$W$2:$W$9427,Data!$Z$2:$Z$9427,A6) -> 127438 | C6: =SUMIFS(Data!$V$2:$V$9427,Data!$Z$2:$Z$9427,A6) -> 11627 | D6: =SUMIFS(Data!$T$2:$T$9427,Data!$Z$2:$Z$9427,A6) -> 1376 | E6: 103 | F6: =IFERROR(B6/B5-1,0) -> 0
A7: 42795 | B7: =SUMIFS(Data!$W$2:$W$9427,Data!$Z$2:$Z$9427,A7) -> 141099 | C7: =SUMIFS(Data!$V$2:$V$9427,Data!$Z$2:$Z$9427,A7) -> -30577 | D7: =SUMIFS(Data!$T$2:$T$9427,Data!$Z$2:$Z$9427,A7) -> 1471 | E7: 122 | F7: =IFERROR(B7/B6-1,0) -> 0
A8: 42826 | B8: =SUMIFS(Data!$W$2:$W$9427,Data!$Z$2:$Z$9427,A8) -> 129980 | C8: =SUMIFS(Data!$V$2:$V$9427,Data!$Z$2:$Z$9427,A8) -> 4629 | D8: =SUMIFS(Data!$T$2:$T$9427,Data!$Z$2:$Z$9427,A8) -> 1635 | E8: 120 | F8: =IFERROR(B8/B7-1,0) -> 0
A9: 42856 | B9: =SUMIFS(Data!$W$2:$W$9427,Data!$Z$2:$Z$9427,A9) -> 99508 | C9: =SUMIFS(Data!$V$2:$V$9427,Data!$Z$2:$Z$9427,A9) -> 10211 | D9: =SUMIFS(Data!$T$2:$T$9427,Data!$Z$2:$Z$9427,A9) -> 2104 | E9: 116 | F9: =IFERROR(B9/B8-1,0) -> 0
A10: 42887 | B10: =SUMIFS(Data!$W$2:$W$9427,Data!$Z$2:$Z$9427,A10) -> 142801 | C10: =SUMIFS(Data!$V$2:$V$9427,Data!$Z$2:$Z$9427,A10) -> 24407 | D10: =SUMIFS(Data!$T$2:$T$9427,Data!$Z$2:$Z$9427,A10) -> 1985 | E10: 106 | F10: =IFERROR(B10/B9-1,0) -> 0
A11: 42917 | B11: =SUMIFS(Data!$W$2:$W$9427,Data!$Z$2:$Z$9427,A11) -> 132800 | C11: =SUMIFS(Data!$V$2:$V$9427,Data!$Z$2:$Z$9427,A11) -> 6244 | D11: =SUMIFS(Data!$T$2:$T$9427,Data!$Z$2:$Z$9427,A11) -> 1910 | E11: 118 | F11: =IFERROR(B11/B10-1,0) -> 0
A12: 42948 | B12: =SUMIFS(Data!$W$2:$W$9427,Data!$Z$2:$Z$9427,A12) -> 190990 | C12: =SUMIFS(Data!$V$2:$V$9427,Data!$Z$2:$Z$9427,A12) -> 28450 | D12: =SUMIFS(Data!$T$2:$T$9427,Data!$Z$2:$Z$9427,A12) -> 2648 | E12: 121 | F12: =IFERROR(B12/B11-1,0) -> 0
A13: 42979 | B13: =SUMIFS(Data!$W$2:$W$9427,Data!$Z$2:$Z$9427,A13) -> 140529 | C13: =SUMIFS(Data!$V$2:$V$9427,Data!$Z$2:$Z$9427,A13) -> 21946 | D13: =SUMIFS(Data!$T$2:$T$9427,Data!$Z$2:$Z$9427,A13) -> 2130 | E13: 113 | F13: =IFERROR(B13/B12-1,0) -> 0
A14: 43009 | B14: =SUMIFS(Data!$W$2:$W$9427,Data!$Z$2:$Z$9427,A14) -> 243602 | C14: =SUMIFS(Data!$V$2:$V$9427,Data!$Z$2:$Z$9427,A14) -> 51538 | D14: =SUMIFS(Data!$T$2:$T$9427,Data!$Z$2:$Z$9427,A14) -> 2506 | E14: 100 | F14: =IFERROR(B14/B13-1,0) -> 0
A15: 43040 | B15: =SUMIFS(Data!$W$2:$W$9427,Data!$Z$2:$Z$9427,A15) -> 204553 | C15: =SUMIFS(Data!$V$2:$V$9427,Data!$Z$2:$Z$9427,A15) -> 51137 | D15: =SUMIFS(Data!$T$2:$T$9427,Data!$Z$2:$Z$9427,A15) -> 3588 | E15: 107 | F15: =IFERROR(B15/B14-1,0) -> 0
A16: 43070 | B16: =SUMIFS(Data!$W$2:$W$9427,Data!$Z$2:$Z$9427,A16) -> 222027 | C16: =SUMIFS(Data!$V$2:$V$9427,Data!$Z$2:$Z$9427,A16) -> 46445 | D16: =SUMIFS(Data!$T$2:$T$9427,Data!$Z$2:$Z$9427,A16) -> 2206 | E16: 104 | F16: =IFERROR(B16/B15-1,0) -> 0
A17: 43101 | B17: =SUMIFS(Data!$W$2:$W$9427,Data!$Z$2:$Z$9427,A17) -> 126812 | C17: =SUMIFS(Data!$V$2:$V$9427,Data!$Z$2:$Z$9427,A17) -> 5625 | D17: =SUMIFS(Data!$T$2:$T$9427,Data!$Z$2:$Z$9427,A17) -> 1614 | E17: 124 | F17: =IFERROR(B17/B16-1,0) -> 0 | G17: =IFERROR(B17/B5-1,0) -> 0
A18: 43132 | B18: =SUMIFS(Data!$W$2:$W$9427,Data!$Z$2:$Z$9427,A18) -> 88435 | C18: =SUMIFS(Data!$V$2:$V$9427,Data!$Z$2:$Z$9427,A18) -> -4686 | D18: =SUMIFS(Data!$T$2:$T$9427,Data!$Z$2:$Z$9427,A18) -> 1760 | E18: 117 | F18: =IFERROR(B18/B17-1,0) -> 0 | G18: =IFERROR(B18/B6-1,0) -> 0
A19: 43160 | B19: =SUMIFS(Data!$W$2:$W$9427,Data!$Z$2:$Z$9427,A19) -> 63901 | C19: =SUMIFS(Data!$V$2:$V$9427,Data!$Z$2:$Z$9427,A19) -> -3668 | D19: =SUMIFS(Data!$T$2:$T$9427,Data!$Z$2:$Z$9427,A19) -> 1206 | E19: 108 | F19: =IFERROR(B19/B18-1,0) -> 0 | G19: =IFERROR(B19/B7-1,0) -> 0
A20: 43191 | B20: =SUMIFS(Data!$W$2:$W$9427,Data!$Z$2:$Z$9427,A20) -> 73393 | C20: =SUMIFS(Data!$V$2:$V$9427,Data!$Z$2:$Z$9427,A20) -> 5931 | D20: =SUMIFS(Data!$T$2:$T$9427,Data!$Z$2:$Z$9427,A20) -> 1160 | E20: 96 | F20: =IFERROR(B20/B19-1,0) -> 0 | G20: =IFERROR(B20/B8-1,0) -> 0
A21: 43221 | B21: =SUMIFS(Data!$W$2:$W$9427,Data!$Z$2:$Z$9427,A21) -> 156711 | C21: =SUMIFS(Data!$V$2:$V$9427,Data!$Z$2:$Z$9427,A21) -> 26841 | D21: =SUMIFS(Data!$T$2:$T$9427,Data!$Z$2:$Z$9427,A21) -> 2718 | E21: 132 | F21: =IFERROR(B21/B20-1,0) -> 0 | G21: =IFERROR(B21/B9-1,0) -> 0
A22: 43252 | B22: =SUMIFS(Data!$W$2:$W$9427,Data!$Z$2:$Z$9427,A22) -> 100165 | C22: =SUMIFS(Data!$V$2:$V$9427,Data!$Z$2:$Z$9427,A22) -> 27353 | D22: =SUMIFS(Data!$T$2:$T$9427,Data!$Z$2:$Z$9427,A22) -> 1977 | E22: 105 | F22: =IFERROR(B22/B21-1,0) -> 0 | G22: =IFERROR(B22/B10-1,0) -> 0
A23: 43282 | B23: =SUMIFS(Data!$W$2:$W$9427,Data!$Z$2:$Z$9427,A23) -> 118777 | C23: =SUMIFS(Data!$V$2:$V$9427,Data!$Z$2:$Z$9427,A23) -> 17911 | D23: =SUMIFS(Data!$T$2:$T$9427,Data!$Z$2:$Z$9427,A23) -> 1965 | E23: 120 | F23: =IFERROR(B23/B22-1,0) -> 0 | G23: =IFERROR(B23/B11-1,0) -> 0
A24: 43313 | B24: =SUMIFS(Data!$W$2:$W$9427,Data!$Z$2:$Z$9427,A24) -> 119726 | C24: =SUMIFS(Data!$V$2:$V$9427,Data!$Z$2:$Z$9427,A24) -> 36850 | D24: =SUMIFS(Data!$T$2:$T$9427,Data!$Z$2:$Z$9427,A24) -> 2802 | E24: 132 | F24: =IFERROR(B24/B23-1,0) -> 0 | G24: =IFERROR(B24/B12-1,0) -> 0
A25: 43344 | B25: =SUMIFS(Data!$W$2:$W$9427,Data!$Z$2:$Z$9427,A25) -> 308372 | C25: =SUMIFS(Data!$V$2:$V$9427,Data!$Z$2:$Z$9427,A25) -> 33559 | D25: =SUMIFS(Data!$T$2:$T$9427,Data!$Z$2:$Z$9427,A25) -> 3572 | E25: 149 | F25: =IFERROR(B25/B24-1,0) -> 0 | G25: =IFERROR(B25/B13-1,0) -> 0
A26: 43374 | B26: =SUMIFS(Data!$W$2:$W$9427,Data!$Z$2:$Z$9427,A26) -> 269415 | C26: =SUMIFS(Data!$V$2:$V$9427,Data!$Z$2:$Z$9427,A26) -> 36604 | D26: =SUMIFS(Data!$T$2:$T$9427,Data!$Z$2:$Z$9427,A26) -> 3666 | E26: 126 | F26: =IFERROR(B26/B25-1,0) -> 0 | G26: =IFERROR(B26/B14-1,0) -> 0
A27: 43405 | B27: =SUMIFS(Data!$W$2:$W$9427,Data!$Z$2:$Z$9427,A27) -> 312630 | C27: =SUMIFS(Data!$V$2:$V$9427,Data!$Z$2:$Z$9427,A27) -> 63190 | D27: =SUMIFS(Data!$T$2:$T$9427,Data!$Z$2:$Z$9427,A27) -> 4414 | E27: 119 | F27: =IFERROR(B27/B26-1,0) -> 0 | G27: =IFERROR(B27/B15-1,0) -> 0
A28: 43435 | B28: =SUMIFS(Data!$W$2:$W$9427,Data!$Z$2:$Z$9427,A28) -> 206210 | C28: =SUMIFS(Data!$V$2:$V$9427,Data!$Z$2:$Z$9427,A28) -> 52348 | D28: =SUMIFS(Data!$T$2:$T$9427,Data!$Z$2:$Z$9427,A28) -> 2780 | E28: 126 | F28: =IFERROR(B28/B27-1,0) -> 0 | G28: =IFERROR(B28/B16-1,0) -> 0
... A52: 44166 | B52: =SUMIFS(Data!$W$2:$W$9427,Data!$Z$2:$Z$9427,A52) -> 253356 | C52: =SUMIFS(Data!$V$2:$V$9427,Data!$Z$2:$Z$9427,A52) -> 58635 | D52: =SUMIFS(Data!$T$2:$T$9427,Data!$Z$2:$Z$9427,A52) -> 3823 | E52: 154 | F52: =IFERROR(B52/B51-1,0) -> 0 | G52: =IFERROR(B52/B40-1,0) -> 0

Sheet Category Summary
A1: CATEGORY SUMMARY
A2: PivotTable-like formula summary. These are not native PivotTables.
A4: Category | B4: Sales | C4: Profit | D4: Units | E4: Profit Margin
A5: Appliances | B5: =SUMIF(Data!$A$2:$A$9427,A5,Data!$W$2:$W$9427) -> 456736 | C5: =SUMIF(Data!$A$2:$A$9427,A5,Data!$V$2:$V$9427) -> 121641 | D5: =SUMIF(Data!$A$2:$A$9427,A5,Data!$T$2:$T$9427) -> 7040 | E5: =IFERROR(C5/B5,0) -> 0.26632672
A6: Binders and Binder Accessories | B6: =SUMIF(Data!$A$2:$A$9427,A6,Data!$W$2:$W$9427) -> 638583 | C6: =SUMIF(Data!$A$2:$A$9427,A6,Data!$V$2:$V$9427) -> 226582 | D6: =SUMIF(Data!$A$2:$A$9427,A6,Data!$T$2:$T$9427) -> 13239 | E6: =IFERROR(C6/B6,0) -> 0.35481997
A7: Bookcases | B7: =SUMIF(Data!$A$2:$A$9427,A7,Data!$W$2:$W$9427) -> 507496 | C7: =SUMIF(Data!$A$2:$A$9427,A7,Data!$V$2:$V$9427) -> -7714 | D7: =SUMIF(Data!$A$2:$A$9427,A7,Data!$T$2:$T$9427) -> 2694 | E7: =IFERROR(C7/B7,0) -> -0.01520012
A8: Chairs & Chairmats | B8: =SUMIF(Data!$A$2:$A$9427,A8,Data!$W$2:$W$9427) -> 1164586 | C8: =SUMIF(Data!$A$2:$A$9427,A8,Data!$V$2:$V$9427) -> 165341 | D8: =SUMIF(Data!$A$2:$A$9427,A8,Data!$T$2:$T$9427) -> 6325 | E8: =IFERROR(C8/B8,0) -> 0.14197406
A9: Computer Peripherals | B9: =SUMIF(Data!$A$2:$A$9427,A9,Data!$W$2:$W$9427) -> 490851 | C9: =SUMIF(Data!$A$2:$A$9427,A9,Data!$V$2:$V$9427) -> 87911 | D9: =SUMIF(Data!$A$2:$A$9427,A9,Data!$T$2:$T$9427) -> 11735 | E9: =IFERROR(C9/B9,0) -> 0.17909916
A10: Copiers and Fax | B10: =SUMIF(Data!$A$2:$A$9427,A10,Data!$W$2:$W$9427) -> 661215 | C10: =SUMIF(Data!$A$2:$A$9427,A10,Data!$V$2:$V$9427) -> 129154 | D10: =SUMIF(Data!$A$2:$A$9427,A10,Data!$T$2:$T$9427) -> 1177 | E10: =IFERROR(C10/B10,0) -> 0.1953283
A11: Envelopes | B11: =SUMIF(Data!$A$2:$A$9427,A11,Data!$W$2:$W$9427) -> 147915 | C11: =SUMIF(Data!$A$2:$A$9427,A11,Data!$V$2:$V$9427) -> 46133 | D11: =SUMIF(Data!$A$2:$A$9427,A11,Data!$T$2:$T$9427) -> 3959 | E11: =IFERROR(C11/B11,0) -> 0.31188858
A12: Labels | B12: =SUMIF(Data!$A$2:$A$9427,A12,Data!$W$2:$W$9427) -> 23446 | C12: =SUMIF(Data!$A$2:$A$9427,A12,Data!$V$2:$V$9427) -> 17776 | D12: =SUMIF(Data!$A$2:$A$9427,A12,Data!$T$2:$T$9427) -> 4794 | E12: =IFERROR(C12/B12,0) -> 0.7581677
A13: Office Furnishings | B13: =SUMIF(Data!$A$2:$A$9427,A13,Data!$W$2:$W$9427) -> 444634 | C13: =SUMIF(Data!$A$2:$A$9427,A13,Data!$V$2:$V$9427) -> 92216 | D13: =SUMIF(Data!$A$2:$A$9427,A13,Data!$T$2:$T$9427) -> 12446 | E13: =IFERROR(C13/B13,0) -> 0.20739754
A14: Office Machines | B14: =SUMIF(Data!$A$2:$A$9427,A14,Data!$W$2:$W$9427) -> 1218655 | C14: =SUMIF(Data!$A$2:$A$9427,A14,Data!$V$2:$V$9427) -> 168079 | D14: =SUMIF(Data!$A$2:$A$9427,A14,Data!$T$2:$T$9427) -> 4674 | E14: =IFERROR(C14/B14,0) -> 0.13792173
A15: Paper | B15: =SUMIF(Data!$A$2:$A$9427,A15,Data!$W$2:$W$9427) -> 253620 | C15: =SUMIF(Data!$A$2:$A$9427,A15,Data!$V$2:$V$9427) -> 35360 | D15: =SUMIF(Data!$A$2:$A$9427,A15,Data!$T$2:$T$9427) -> 18852 | E15: =IFERROR(C15/B15,0) -> 0.13942118
A16: Pens & Art Supplies | B16: =SUMIF(Data!$A$2:$A$9427,A16,Data!$W$2:$W$9427) -> 103265 | C16: =SUMIF(Data!$A$2:$A$9427,A16,Data!$V$2:$V$9427) -> 1202 | D16: =SUMIF(Data!$A$2:$A$9427,A16,Data!$T$2:$T$9427) -> 10752 | E16: =IFERROR(C16/B16,0) -> 0.011639955
... A21: Telephones and Communication | B21: =SUMIF(Data!$A$2:$A$9427,A21,Data!$W$2:$W$9427) -> 1144284 | C21: =SUMIF(Data!$A$2:$A$9427,A21,Data!$V$2:$V$9427) -> 297944 | D21: =SUMIF(Data!$A$2:$A$9427,A21,Data!$T$2:$T$9427) -> 14284 | E21: =IFERROR(C21/B21,0) -> 0.26037592

Sheet Region Summary
A1: REGION SUMMARY
A2: PivotTable-like formula summary. These are not native PivotTables.
A4: Region | B4: Sales | C4: Profit | D4: Units | E4: Profit Margin
A5: Central | B5: =SUMIF(Data!$N$2:$N$9427,A5,Data!$W$2:$W$9427) -> 2294603 | C5: =SUMIF(Data!$N$2:$N$9427,A5,Data!$V$2:$V$9427) -> 458668 | D5: =SUMIF(Data!$N$2:$N$9427,A5,Data!$T$2:$T$9427) -> 34979 | E5: =IFERROR(C5/B5,0) -> 0.19988992
A6: East | B6: =SUMIF(Data!$N$2:$N$9427,A6,Data!$W$2:$W$9427) -> 3143122 | C6: =SUMIF(Data!$N$2:$N$9427,A6,Data!$V$2:$V$9427) -> 475024 | D6: =SUMIF(Data!$N$2:$N$9427,A6,Data!$T$2:$T$9427) -> 47296 | E6: =IFERROR(C6/B6,0) -> 0.15113126
A7: South | B7: =SUMIF(Data!$N$2:$N$9427,A7,Data!$W$2:$W$9427) -> 1511949 | C7: =SUMIF(Data!$N$2:$N$9427,A7,Data!$V$2:$V$9427) -> 107145 | D7: =SUMIF(Data!$N$2:$N$9427,A7,Data!$T$2:$T$9427) -> 21583 | E7: =IFERROR(C7/B7,0) -> 0.070865486
A8: West | B8: =SUMIF(Data!$N$2:$N$9427,A8,Data!$W$2:$W$9427) -> 2002353 | C8: =SUMIF(Data!$N$2:$N$9427,A8,Data!$V$2:$V$9427) -> 271578 | D8: =SUMIF(Data!$N$2:$N$9427,A8,Data!$T$2:$T$9427) -> 26206 | E8: =IFERROR(C8/B8,0) -> 0.13562943

Sheet Lists
A1: All | B1: All
A2: Central | B2: Appliances
A3: East | B3: Binders and Binder Accessories
A4: South | B4: Bookcases
A5: West | B5: Chairs & Chairmats
B6: Computer Peripherals
B7: Copiers and Fax
B8: Envelopes
B9: Labels
B10: Office Furnishings
B11: Office Machines
B12: Paper
B13: Pens & Art Supplies
B14: Rubber Bands
B15: Scissors, Rulers and Trimmers
B16: Storage & Organization
B17: Tables
B18: Telephones and Communication

Sheet Dashboard
B2: SALES PERFORMANCE DASHBOARD
B3: SUPERSTORE | 2017–2020 | Select filters to update headline metrics
B5: Region filter | C5: All | E5: Category filter | F5: All
B7: TOTAL SALES | E7: PROFIT | H7: UNITS SOLD | K7: ORDERS | N7: PROFIT MARGIN
B8: =SUMPRODUCT((IF($C$5="All",1,--(Data!$N$2:$N$9427=$C$5)))*(IF($F$5="All",1,--(Data!$A$2:$A$9427=$F$5)))*Data!$W$2:$W$9427) -> 0 | E8: =SUMPRODUCT((IF($C$5="All",1,--(Data!$N$2:$N$9427=$C$5)))*(IF($F$5="All",1,--(Data!$A$2:$A$9427=$F$5)))*Data!$V$2:$V$9427) -> 0 | H8: =SUMPRODUCT((IF($C$5="All",1,--(Data!$N$2:$N$9427=$C$5)))*(IF($F$5="All",1,--(Data!$A$2:$A$9427=$F$5)))*Data!$T$2:$T$9427) -> 0 | K8: {=IFERROR(ROWS(_xlfn.UNIQUE(_xlfn._xlws.FILTER(Data!$K$2:$K$9427,(IF($C$5="All",1,Data!$N$2:$N$9427=$C$5))*(IF($F$5="All",1,Data!$A$2:$A$9427=$F$5))))),0)} -> 0 | N8: =IFERROR(E8/B8,0) -> 0
B11: MONTHLY SALES & PROFIT | I11: SALES BY CATEGORY
B29: HOW TO READ THIS DASHBOARD
B30: Use the yellow dropdowns to recalculate headline KPIs. Monthly, category and region detail is on the summary tabs. Filter transactions directly on Data.
B33: Source: public Superstore sample (2017–2020); details and metric notes are on Read Me.

Sheet Read Me
A1: WORKBOOK GUIDE & DATA NOTES
A2: Dataset source | B2: Public Superstore CSV from PacktPublishing, Learning Tableau 2025 6E, Chapter 16: https://github.com/PacktPublishing/Learning-Tableau-2025-6E/blob/main/Chapter_16/Superstore.csv
A3: Coverage | B3: 9,426 unique transaction rows; order dates Jan 01, 2017 to Dec 28, 2020. Original attachment was unavailable locally; this verified public sample is used.
A4: Dashboard | B4: Yellow dropdowns filter headline metrics by Region and Category. Charts show full-dataset monthly trend and category mix. Use the Data table filter for transaction exploration.
A5: Data | B5: One row per source record in a filterable Excel Table. Month Start, Year and Profit Margin are calculated with in-sheet formulas.
A6: Monthly Trends | B6: Formula-driven monthly sales, profit, units, distinct order count, MoM sales growth and YoY sales growth. Growth is blank until a prior comparison exists.
A7: Category / Region Summary | B7: SUMIF formula rollups that function like PivotTable summaries; these are not native Excel PivotTables.
A8: Metrics | B8: Sales and Profit are sums of source fields; Units Sold sums Order Quantity; Orders are distinct Order ID counts in the monthly rollup. Dashboard Orders KPI sums line-level Order ID values and should be treated as order-line volume.
A9: Refresh | B9: Static sample. To update, replace rows in the Data table while retaining its columns, then recalculate formulas in Excel.
